python_code_outline/__init__.py
python_code_outline/py.typed
python_code_outline/python_report_generator.py
python_code_outline-0.1.9.dist-info/LICENSE
python_code_outline-0.1.9.dist-info/METADATA
python_code_outline-0.1.9.dist-info/WHEEL
python_code_outline-0.1.9.dist-info/RECORD
